mosromgr/__init__.py
mosromgr/cli.py
mosromgr/exc.py
mosromgr/moscollection.py
mosromgr/moselements.py
mosromgr/mostypes.py
mosromgr/utils/__init__.py
mosromgr/utils/s3.py
mosromgr/utils/xml.py
mosromgr-0.10.0.dist-info/LICENSE.txt
mosromgr-0.10.0.dist-info/METADATA
mosromgr-0.10.0.dist-info/WHEEL
mosromgr-0.10.0.dist-info/entry_points.txt
mosromgr-0.10.0.dist-info/top_level.txt
mosromgr-0.10.0.dist-info/RECORD
