Metadata-Version: 2.1
Name: mosromgr
Version: 0.10.0
Summary: Python library for managing MOS running orders
Home-page: https://www.bbc.co.uk/opensource/projects/mosromgr
Author: BBC News Labs
Author-email: bbcnewslabsteam@bbc.co.uk
License: Apache-2.0
Project-URL: Documentation, https://mosromgr.readthedocs.io/
Project-URL: Source Code, https://github.com/bbc/mosromgr
Project-URL: Issue Tracker, https://github.com/bbc/mosromgr/issues
Keywords: mos,mosprotocol,bbc,openmedia,runningorder
Platform: UNKNOWN
Classifier: Development Status :: 4 - Beta
Classifier: Operating System :: POSIX
Classifier: Operating System :: Unix
Classifier: License :: OSI Approved :: Apache Software License
Classifier: Programming Language :: Python :: 3
Classifier: Programming Language :: Python :: 3 :: Only
Classifier: Programming Language :: Python :: 3.6
Classifier: Programming Language :: Python :: 3.7
Classifier: Programming Language :: Python :: 3.8
Classifier: Programming Language :: Python :: 3.9
Classifier: Programming Language :: Python :: 3.10
Classifier: Topic :: Utilities
Requires-Python: >=3.6
Requires-Dist: setuptools
Requires-Dist: boto3
Requires-Dist: xmltodict
Requires-Dist: python-dateutil
Provides-Extra: doc
Requires-Dist: graphviz ; extra == 'doc'
Requires-Dist: sphinx ; extra == 'doc'
Requires-Dist: sphinx-rtd-theme ; extra == 'doc'
Provides-Extra: test
Requires-Dist: pytest ; extra == 'test'
Requires-Dist: coverage ; extra == 'test'
Requires-Dist: mock ; extra == 'test'
Requires-Dist: pylint ; extra == 'test'
Requires-Dist: tox ; extra == 'test'
